okipy/__init__.py
okipy/colors.py
okipy/lib.py
okipy/main.py
okipy/py.typed
okipy/strategies.py
okipy/utils.py
okipy-1.2.0.dist-info/LICENCE
okipy-1.2.0.dist-info/METADATA
okipy-1.2.0.dist-info/WHEEL
okipy-1.2.0.dist-info/entry_points.txt
okipy-1.2.0.dist-info/top_level.txt
okipy-1.2.0.dist-info/RECORD
