Metadata-Version: 2.2
Name: okipy
Version: 1.2.0
Summary: Minimal, typed, functional and dynamic test library.
Author-email: Matthieu Jolimaitre <matthieu@imagevo.fr>
Project-URL: Homepage, https://git.barnulf.net/mb/okipy
Keywords: test,functional,library,testing,dynamic,minimal
Classifier: License :: OSI Approved :: MIT License
Classifier: Programming Language :: Python
Classifier: Programming Language :: Python :: 3
Classifier: Operating System :: OS Independent
Requires-Python: >=3.9
License-File: LICENCE
